{
  "signals": {
    "action": 0.2664,
    "mainstream": 0.4161,
    "crime": 0.2564,
    "thriller": 0.4245,
    "drama": 0.9763,
    "scifi": 0.5219,
    "visual": 0.5423,
    "comedy": 0.7337,
    "romance": 0.1938,
    "arthouse": 0.2975,
    "international": 0.0255,
    "horror": 0.1881,
    "european": 0.1808,
    "classic": 0.0863,
    "animation": 0.3083,
    "intense": 0.058,
    "documentary": 0.0216,
    "indie": 0.1134,
    "surreal": 0.0209,
    "social": 0.0255
  },
  "totalRatings": 1086,
  "tmdbRatings": 16,
  "lastSync": "2026-05-10T08:10:56.877236",
  "ratedTitles": [
    {
      "id": 279,
      "rating": 9.0,
      "title": "Amadeus"
    },
    {
      "id": 14,
      "rating": 9.0,
      "title": "American Beauty"
    },
    {
      "id": 73,
      "rating": 9.0,
      "title": "American History X"
    },
    {
      "id": 68726,
      "rating": 5.0,
      "title": "Pacific Rim"
    },
    {
      "id": 78,
      "rating": 8.0,
      "title": "Blade Runner"
    },
    {
      "id": 933260,
      "rating": 7.0,
      "title": "The Substance"
    },
    {
      "id": 680,
      "rating": 10.0,
      "title": "Pulp Fiction"
    },
    {
      "id": 340837,
      "rating": 8.0,
      "title": "A Cure for Wellness"
    },
    {
      "id": 844,
      "rating": 8.0,
      "title": "2046"
    },
    {
      "id": 502033,
      "rating": 6.0,
      "title": "Sound of Metal"
    },
    {
      "id": 438631,
      "rating": 7.0,
      "title": "Dune"
    },
    {
      "id": 475557,
      "rating": 6.0,
      "title": "Joker"
    },
    {
      "id": 399566,
      "rating": 5.0,
      "title": "Godzilla vs. Kong"
    },
    {
      "id": 83533,
      "rating": 3.0,
      "title": "Avatar: Fire and Ash"
    },
    {
      "id": 54155,
      "rating": 5.0,
      "title": "Hanna"
    },
    {
      "id": 202411,
      "rating": 7.0,
      "title": "Monarch: Legacy of Monsters"
    }
  ]
}